mm_json/__init__.py
mm_json/_private/__init__.py
mm_json/_private/conversions.py
mm_json/mm/__init__.py
mm_json/mm/fields.py
mm_json/mm/typing.py
mm_json/public/__init__.py
mm_json/public/dataclass_json.py
mm_json/public/dataclasses_json.py
mm_json/public/typing_json.py
mm_json-0.0.0.dist-info/LICENSE
mm_json-0.0.0.dist-info/METADATA
mm_json-0.0.0.dist-info/WHEEL
mm_json-0.0.0.dist-info/entry_points.txt
mm_json-0.0.0.dist-info/top_level.txt
mm_json-0.0.0.dist-info/RECORD
